[
  {
    "userId": "github-81183022",
    "name": null,
    "avatar": "https://avatars.githubusercontent.com/u/81183022?v=4",
    "content": "First comment",
    "createdAt": 1618390083391,
    "id": "24aueOKzD7bys4ltBsWy0-WpBzh19R"
  },
  {
    "userId": "github-81183022",
    "name": null,
    "avatar": "https://avatars.githubusercontent.com/u/81183022?v=4",
    "content": "second",
    "createdAt": 1618390100557,
    "id": "WLcz_LJhUXrQMyBa4z7Bsiv3zxAKYF"
  },
  {
    "userId": "github-81183022",
    "name": null,
    "avatar": "https://avatars.githubusercontent.com/u/81183022?v=4",
    "content": "third",
    "createdAt": 1618390119594,
    "id": "idlotIJlA1QSQlcuK3vSIwsuO4t1WY"
  },
  {
    "userId": "github-81183022",
    "name": null,
    "avatar": "https://avatars.githubusercontent.com/u/81183022?v=4",
    "content": "vier\n",
    "createdAt": 1618390453726,
    "id": "lbINmb0Ev6trZdG_rPQysqrBTvKSNl"
  },
  {
    "userId": "github-81183022",
    "name": null,
    "avatar": "https://avatars.githubusercontent.com/u/81183022?v=4",
    "content": "vijf",
    "createdAt": 1618390459683,
    "id": "0fGCWeogmVBP92_vDs3h7OY8zu_6k-"
  }
]