[
  {
    "userId": "github-81183022",
    "name": null,
    "avatar": "https://avatars.githubusercontent.com/u/81183022?v=4",
    "content": "First comment",
    "createdAt": 1618390083391,
    "id": "24aueOKzD7bys4ltBsWy0-WpBzh19R"
  },
  {
    "userId": "github-81183022",
    "name": null,
    "avatar": "https://avatars.githubusercontent.com/u/81183022?v=4",
    "content": "second",
    "createdAt": 1618390100557,
    "id": "WLcz_LJhUXrQMyBa4z7Bsiv3zxAKYF"
  },
  {
    "userId": "github-81183022",
    "name": null,
    "avatar": "https://avatars.githubusercontent.com/u/81183022?v=4",
    "content": "third",
    "createdAt": 1618390119594,
    "id": "idlotIJlA1QSQlcuK3vSIwsuO4t1WY"
  },
  {
    "userId": "github-81183022",
    "name": null,
    "avatar": "https://avatars.githubusercontent.com/u/81183022?v=4",
    "content": "vier\n",
    "createdAt": 1618390453726,
    "id": "lbINmb0Ev6trZdG_rPQysqrBTvKSNl"
  },
  {
    "userId": "github-81183022",
    "name": null,
    "avatar": "https://avatars.githubusercontent.com/u/81183022?v=4",
    "content": "vijf",
    "createdAt": 1618390459683,
    "id": "0fGCWeogmVBP92_vDs3h7OY8zu_6k-"
  },
  {
    "userId": "github-81183022",
    "name": null,
    "avatar": "https://avatars.githubusercontent.com/u/81183022?v=4",
    "content": "zes",
    "createdAt": 1618390493405,
    "id": "8qox6mo7NgfAEVwjFsIR2VnkBeswjx"
  },
  {
    "userId": "github-81183022",
    "name": null,
    "avatar": "https://avatars.githubusercontent.com/u/81183022?v=4",
    "content": "zeven",
    "createdAt": 1618390538011,
    "id": "4gmTd2XuDFOMUZcvrtBS7dVXy4yf16"
  },
  {
    "userId": "github-81183022",
    "name": null,
    "avatar": "https://avatars.githubusercontent.com/u/81183022?v=4",
    "content": "acht",
    "createdAt": 1618390549449,
    "id": "j-myr5umOGw5kEae1dWSUxpLWQe_Sq"
  },
  {
    "userId": "github-81183022",
    "name": null,
    "avatar": "https://avatars.githubusercontent.com/u/81183022?v=4",
    "content": "1",
    "createdAt": 1618392487996,
    "id": "EWKG8n7p6Rjm7i33lyWn0Ay0JJNI1a"
  },
  {
    "userId": "github-81183022",
    "name": null,
    "avatar": "https://avatars.githubusercontent.com/u/81183022?v=4",
    "content": "1",
    "createdAt": 1618392489383,
    "id": "hZaMcTYIBvuu2ID9Xv0r7Awx6rQXSs"
  }
]